commitizen_r_provider-0.2.0.dist-info/licenses/LICENSE
r_provider/__init__.py
r_provider/r_provider.py
commitizen_r_provider-0.2.0.dist-info/METADATA
commitizen_r_provider-0.2.0.dist-info/WHEEL
commitizen_r_provider-0.2.0.dist-info/entry_points.txt
commitizen_r_provider-0.2.0.dist-info/top_level.txt
commitizen_r_provider-0.2.0.dist-info/RECORD
