Metadata-Version: 2.4
Name: commitizen-r-provider
Version: 0.2.0
Summary: An R provider for commitizen
Author-email: camille-s <camille.seaberry@gmail.com>
License-Expression: MIT
Project-URL: Homepage, https://github.com/camille-s/commitizen-r-provider
Project-URL: Bug Reports, https://github.com/camille-s/commitizen-r-provider/issues
Project-URL: Source, https://github.com/camille-s/commitizen-r-provider
Classifier: Programming Language :: Python :: 3
Classifier: Operating System :: OS Independent
Classifier: Development Status :: 4 - Beta
Classifier: Intended Audience :: Developers
Classifier: Topic :: Software Development :: Version Control
Requires-Python: >=3.10
License-File: LICENSE
Requires-Dist: commitizen
Dynamic: license-file
